{
    "enemy_skill_id": 15238,
    "jp_skill": {
        "enemy_skill_id": 15238,
        "flags": 16386,
        "name": "すぐ片づけるッス！",
        "params": [
            null,
            3,
            null,
            null,
            null,
            null,
            null,
            null,
            null,
            null,
            null,
            null,
            null,
            null,
            100,
            null
        ],
        "type": 60
    },
    "kr_skill": {
        "enemy_skill_id": 15238,
        "flags": 16386,
        "name": "すぐ片づけるッス！",
        "params": [
            null,
            3,
            null,
            null,
            null,
            null,
            null,
            null,
            null,
            null,
            null,
            null,
            null,
            null,
            100,
            null
        ],
        "type": 60
    },
    "na_skill": {
        "enemy_skill_id": 15238,
        "flags": 16386,
        "name": "すぐ片づけるッス！",
        "params": [
            null,
            3,
            null,
            null,
            null,
            null,
            null,
            null,
            null,
            null,
            null,
            null,
            null,
            null,
            100,
            null
        ],
        "type": 60
    }
}