{
    "enemy_skill_id": 2829,
    "jp_skill": {
        "enemy_skill_id": 2829,
        "flags": 7,
        "name": "古龍族の冥呪",
        "params": [
            "6ターンの間、スキル使用不能",
            6,
            6,
            null,
            null,
            null,
            null,
            null,
            null,
            null,
            null,
            null,
            null,
            null,
            null,
            null
        ],
        "type": 14
    },
    "kr_skill": {
        "enemy_skill_id": 2829,
        "flags": 7,
        "name": "고룡족의 명주",
        "params": [
            "6턴 동안 스킬 사용불가",
            6,
            6,
            null,
            null,
            null,
            null,
            null,
            null,
            null,
            null,
            null,
            null,
            null,
            null,
            null
        ],
        "type": 14
    },
    "na_skill": {
        "enemy_skill_id": 2829,
        "flags": 7,
        "name": "Ancient Dragon Tribe's Dark Curse",
        "params": [
            "Skills are unusable for 6 turns",
            6,
            6,
            null,
            null,
            null,
            null,
            null,
            null,
            null,
            null,
            null,
            null,
            null,
            null,
            null
        ],
        "type": 14
    }
}