{
    "enemy_skill_id": 3563,
    "jp_skill": {
        "enemy_skill_id": 3563,
        "flags": 2062,
        "name": "ギフトハリケーン",
        "params": [
            null,
            4,
            4,
            50,
            null,
            null,
            null,
            null,
            null,
            null,
            null,
            20,
            null,
            null,
            null,
            null
        ],
        "type": 15
    },
    "kr_skill": {
        "enemy_skill_id": 3563,
        "flags": 2062,
        "name": "선물 폭풍",
        "params": [
            null,
            4,
            4,
            50,
            null,
            null,
            null,
            null,
            null,
            null,
            null,
            20,
            null,
            null,
            null,
            null
        ],
        "type": 15
    },
    "na_skill": {
        "enemy_skill_id": 3563,
        "flags": 2062,
        "name": "Gift Hurricane",
        "params": [
            null,
            4,
            4,
            50,
            null,
            null,
            null,
            null,
            null,
            null,
            null,
            20,
            null,
            null,
            null,
            null
        ],
        "type": 15
    }
}