{
    "enemy_skill_id": 6917,
    "jp_skill": {
        "enemy_skill_id": 6917,
        "flags": 7,
        "name": "ランダム用セット1",
        "params": [
            "属性が変化した",
            6911,
            6925,
            null,
            null,
            null,
            null,
            null,
            null,
            null,
            null,
            null,
            null,
            null,
            null,
            null
        ],
        "type": 83
    },
    "kr_skill": {
        "enemy_skill_id": 6917,
        "flags": 7,
        "name": "랜덤용 세트1",
        "params": [
            "속성이 변화했다",
            6911,
            6925,
            null,
            null,
            null,
            null,
            null,
            null,
            null,
            null,
            null,
            null,
            null,
            null,
            null
        ],
        "type": 83
    },
    "na_skill": {
        "enemy_skill_id": 6917,
        "flags": 7,
        "name": "Random Set 1",
        "params": [
            "Attribute has changed",
            6911,
            6925,
            null,
            null,
            null,
            null,
            null,
            null,
            null,
            null,
            null,
            null,
            null,
            null,
            null
        ],
        "type": 83
    }
}