{
    "enemy_skill_id": 8636,
    "jp_skill": {
        "enemy_skill_id": 8636,
        "flags": 8192,
        "name": "おらおら！",
        "params": [
            null,
            null,
            null,
            null,
            null,
            null,
            null,
            null,
            null,
            null,
            null,
            null,
            null,
            1,
            null,
            null
        ],
        "type": 66
    },
    "kr_skill": {
        "enemy_skill_id": 8636,
        "flags": 8192,
        "name": "오라오라!",
        "params": [
            null,
            null,
            null,
            null,
            null,
            null,
            null,
            null,
            null,
            null,
            null,
            null,
            null,
            1,
            null,
            null
        ],
        "type": 66
    },
    "na_skill": {
        "enemy_skill_id": 8636,
        "flags": 8192,
        "name": "Come! Come!",
        "params": [
            null,
            null,
            null,
            null,
            null,
            null,
            null,
            null,
            null,
            null,
            null,
            null,
            null,
            1,
            null,
            null
        ],
        "type": 66
    }
}