{
    "_name": "Shirozaki Ichigo 2 times",
    "attack": null,
    "enemy_skill_id": 2825,
    "params": [
        null,
        2802,
        2796,
        2800,
        null,
        null,
        null,
        null,
        null,
        null,
        null,
        null,
        null,
        null,
        null,
        null
    ],
    "skill_ids": [
        2802,
        2796,
        2800
    ],
    "skills": [
        {
            "_name": "This is the true form of Senbonzakura.",
            "attack": null,
            "enemy_skill_id": 2802,
            "params": [
                null,
                null,
                null,
                null,
                null,
                null,
                null,
                null,
                null,
                null,
                null,
                null,
                null,
                null,
                null,
                null
            ],
            "type": 66
        },
        {
            "_name": "Senkei Senbonzakura Kageyoshi",
            "attack": null,
            "enemy_count": 1,
            "enemy_skill_id": 2796,
            "multiplier": 200,
            "params": [
                "ATK becomes 2x",
                1,
                999,
                200,
                null,
                null,
                null,
                null,
                null,
                null,
                null,
                null,
                null,
                null,
                null,
                null
            ],
            "turns": 999,
            "type": 17
        },
        {
            "_name": "You are only the second to ever see it.",
            "attack": null,
            "enemy_skill_id": 2800,
            "params": [
                null,
                null,
                null,
                null,
                null,
                null,
                null,
                null,
                null,
                null,
                null,
                null,
                null,
                null,
                null,
                null
            ],
            "type": 66
        }
    ],
    "type": 83
}