{
    "_name": "アームストロングクライムや!!",
    "attack": null,
    "enemy_skill_id": 14152,
    "extra_description": null,
    "params": [
        "3ターンの間、対象箇所のドロップが変化する",
        3,
        50,
        null,
        null,
        63,
        null,
        null,
        null,
        null,
        null,
        null,
        null,
        null,
        null,
        null
    ],
    "position_cols": null,
    "position_rows": [
        3
    ],
    "position_str": [
        "XXXXXX",
        "XXXXXX",
        "OOOOOO",
        "XXXXXX",
        "XXXXXX"
    ],
    "speed": 50,
    "turns": 3,
    "type": 110
}