{
    "_name": "******",
    "attack": null,
    "enemy_skill_id": 10618,
    "extra_description": null,
    "params": [
        null,
        10616,
        10617,
        null,
        null,
        null,
        null,
        null,
        null,
        null,
        null,
        null,
        null,
        null,
        null,
        null
    ],
    "skill_ids": [
        10616,
        10617
    ],
    "skills": [
        {
            "_name": "******",
            "attack": null,
            "enemy_skill_id": 10616,
            "extra_description": null,
            "params": [
                "******",
                1,
                null,
                null,
                null,
                null,
                null,
                null,
                null,
                null,
                null,
                null,
                null,
                null,
                null,
                null
            ],
            "type": 101
        },
        {
            "_name": "******",
            "attack": null,
            "attributes": [
                0,
                1,
                2,
                3,
                4,
                5,
                6,
                7,
                8
            ],
            "count": 10,
            "enemy_skill_id": 10617,
            "extra_description": null,
            "params": [
                "******",
                511,
                10,
                null,
                null,
                null,
                null,
                null,
                null,
                null,
                null,
                null,
                null,
                null,
                null,
                null
            ],
            "type": 94
        }
    ],
    "type": 83
}