{
    "_name": "선제 2회 안타레스",
    "attack": null,
    "enemy_skill_id": 9820,
    "params": [
        null,
        9818,
        9819,
        null,
        null,
        null,
        null,
        null,
        null,
        null,
        null,
        null,
        null,
        null,
        null,
        null
    ],
    "skill_ids": [
        9818,
        9819
    ],
    "skills": [
        {
            "_name": "보거라",
            "attack": null,
            "attributes": [
                7
            ],
            "chance": 20,
            "enemy_skill_id": 9818,
            "max_turns": 5,
            "min_turns": 5,
            "params": [
                "5턴 동안 독드롭이 발생",
                128,
                5,
                5,
                20,
                null,
                null,
                null,
                null,
                null,
                null,
                null,
                null,
                null,
                null,
                null
            ],
            "type": 68
        },
        {
            "_name": "이 수많은 유성들을",
            "attack": null,
            "attributes": [
                7
            ],
            "chance": 100,
            "enemy_skill_id": 9819,
            "max_turns": 30,
            "min_turns": 30,
            "params": [
                "30턴 동안 독드롭이 잠금 상태로 출현한다",
                128,
                30,
                30,
                100,
                null,
                null,
                null,
                null,
                null,
                null,
                null,
                null,
                null,
                null,
                null
            ],
            "type": 96
        }
    ],
    "type": 83
}