{
    "en_text": "Deal 30000 Fire damage to all enemies",
    "jp_skill": {
        "attribute": 0,
        "damage": 30000,
        "levels": 6,
        "mass_attack": true,
        "name": "ブラストカノン",
        "raw_description": "",
        "skill_id": 1031,
        "skill_type": 1,
        "turn_max": 20,
        "turn_min": 15
    },
    "kr_skill": {
        "attribute": 0,
        "damage": 30000,
        "levels": 6,
        "mass_attack": true,
        "name": "블래스트 캐논",
        "raw_description": "",
        "skill_id": 1031,
        "skill_type": 1,
        "turn_max": 20,
        "turn_min": 15
    },
    "na_skill": {
        "attribute": 0,
        "damage": 30000,
        "levels": 6,
        "mass_attack": true,
        "name": "Blast Cannon",
        "raw_description": "",
        "skill_id": 1031,
        "skill_type": 1,
        "turn_max": 20,
        "turn_min": 15
    },
    "skill_id": 1031,
    "skill_type_tags": [
        "AsCondition.MASSIVE_ATTACK"
    ]
}