{
    "en_text": "Unlock all orbs",
    "jp_skill": {
        "levels": null,
        "name": "",
        "raw_description": "",
        "skill_id": 10390,
        "skill_type": 172,
        "turn_max": null,
        "turn_min": null
    },
    "kr_skill": {
        "levels": null,
        "name": "_마하라기다인",
        "raw_description": "",
        "skill_id": 10390,
        "skill_type": 172,
        "turn_max": null,
        "turn_min": null
    },
    "na_skill": {
        "levels": null,
        "name": "",
        "raw_description": "",
        "skill_id": 10390,
        "skill_type": 172,
        "turn_max": null,
        "turn_min": null
    },
    "skill_id": 10390,
    "skill_type_tags": [
        "ASCondition.REMOVE_LOCK"
    ]
}