{
    "en_text": "For 1 turn, Jammer orbs are more likely to appear by 20%; Replace all orbs",
    "jp_skill": {
        "child_ids": [
            14722,
            14721
        ],
        "child_skills": [
            {
                "duration": 1,
                "levels": null,
                "name": "",
                "orbs": [
                    6
                ],
                "percentage": 0.2,
                "raw_description": "",
                "skill_id": 14722,
                "skill_type": 126,
                "turn_max": null,
                "turn_min": null
            },
            {
                "levels": null,
                "name": "",
                "raw_description": "",
                "skill_id": 14721,
                "skill_type": 10,
                "turn_max": null,
                "turn_min": null
            }
        ],
        "levels": 6,
        "name": "トリックフラッシュ",
        "raw_description": "1ターンの間、お邪魔ドロップが少し落ちやすくなる。 ランダムでドロップを入れ替える。",
        "skill_id": 14720,
        "skill_type": 116,
        "turn_max": 11,
        "turn_min": 6
    },
    "kr_skill": {
        "child_ids": [
            14722,
            14721
        ],
        "child_skills": [
            {
                "duration": 1,
                "levels": null,
                "name": "__트릭 플래쉬",
                "orbs": [
                    6
                ],
                "percentage": 0.2,
                "raw_description": "",
                "skill_id": 14722,
                "skill_type": 126,
                "turn_max": null,
                "turn_min": null
            },
            {
                "levels": null,
                "name": "_트릭 플래쉬",
                "raw_description": "",
                "skill_id": 14721,
                "skill_type": 10,
                "turn_max": null,
                "turn_min": null
            }
        ],
        "levels": 6,
        "name": "트릭 플래쉬",
        "raw_description": "1턴 동안 방해드롭의 출현 확률이 조금 높아진다 랜덤으로 드롭을 바꾼다",
        "skill_id": 14720,
        "skill_type": 116,
        "turn_max": 11,
        "turn_min": 6
    },
    "na_skill": {
        "child_ids": [
            14722,
            14721
        ],
        "child_skills": [
            {
                "duration": 1,
                "levels": null,
                "name": "",
                "orbs": [
                    6
                ],
                "percentage": 0.2,
                "raw_description": "",
                "skill_id": 14722,
                "skill_type": 126,
                "turn_max": null,
                "turn_min": null
            },
            {
                "levels": null,
                "name": "",
                "raw_description": "",
                "skill_id": 14721,
                "skill_type": 10,
                "turn_max": null,
                "turn_min": null
            }
        ],
        "levels": 6,
        "name": "Trick Flash",
        "raw_description": "Jammers more likely to appear for 1 turn; replaces all Orbs",
        "skill_id": 14720,
        "skill_type": 116,
        "turn_max": 11,
        "turn_min": 6
    },
    "skill_id": 14720,
    "skill_type_tags": [
        "ASCondition.DROP_CHANCE",
        "ASCondition.ORB_REFRESH"
    ]
}