{
    "en_text": "3.5x ATK when matching 5 Light or Dark orbs in L shape",
    "jp_skill": {
        "_atk": 3.5,
        "_hp": 1,
        "_rcv": 1.0,
        "_shield": 0.0,
        "attributes": [
            3,
            4
        ],
        "name": "",
        "raw_description": "",
        "skill_id": 13977,
        "skill_type": 193,
        "tags": []
    },
    "kr_skill": {
        "_atk": 3.5,
        "_hp": 1,
        "_rcv": 1.0,
        "_shield": 0.0,
        "attributes": [
            3,
            4
        ],
        "name": "__나는 벌 같은 건 내리지 않아요…",
        "raw_description": "",
        "skill_id": 13977,
        "skill_type": 193,
        "tags": []
    },
    "na_skill": {
        "_atk": 3.5,
        "_hp": 1,
        "_rcv": 1.0,
        "_shield": 0.0,
        "attributes": [
            3,
            4
        ],
        "name": "",
        "raw_description": "",
        "skill_id": 13977,
        "skill_type": 193,
        "tags": []
    },
    "skill_id": 13977,
    "skill_type_tags": [
        "LSCondition.ENHANCED_ATK"
    ]
}