{
    "en_text": "1.25x ATK & RCV for Devil type; 3x ATK when matching Water+Dark(Dark+Dark)",
    "jp_skill": {
        "_atk": 1,
        "_hp": 1,
        "_rcv": 1,
        "_shield": 0,
        "child_ids": [
            2242,
            2342
        ],
        "child_skills": [
            {
                "_atk": 1.25,
                "_hp": 1.0,
                "_rcv": 1.25,
                "_shield": 0.0,
                "attributes": [],
                "name": "",
                "raw_description": "",
                "reduction_attributes": [],
                "skill_id": 2242,
                "skill_type": 129,
                "types": [
                    7
                ]
            },
            {
                "_atk": 3.0,
                "_hp": 1,
                "_rcv": 1,
                "_shield": 0,
                "atk_step": 0.0,
                "match_attributes": [
                    1,
                    4,
                    4
                ],
                "max_atk": 3.0,
                "max_combo": 3,
                "min_atk": 3.0,
                "min_combo": 2,
                "name": "",
                "raw_description": "",
                "skill_id": 2342,
                "skill_type": 124
            }
        ],
        "name": "魔召の伝令",
        "raw_description": "悪魔タイプの攻撃力と回復力がほんの少し上昇。 闇闇（闇水）の2コンボ以上で攻撃力が3倍。",
        "skill_id": 2472,
        "skill_type": 138
    },
    "kr_skill": {
        "_atk": 1,
        "_hp": 1,
        "_rcv": 1,
        "_shield": 0,
        "child_ids": [
            2242,
            2342
        ],
        "child_skills": [
            {
                "_atk": 1.25,
                "_hp": 1.0,
                "_rcv": 1.25,
                "_shield": 0.0,
                "attributes": [],
                "name": "_어둠의 천사",
                "raw_description": "",
                "reduction_attributes": [],
                "skill_id": 2242,
                "skill_type": 129,
                "types": [
                    7
                ]
            },
            {
                "_atk": 3.0,
                "_hp": 1,
                "_rcv": 1,
                "_shield": 0,
                "atk_step": 0.0,
                "match_attributes": [
                    1,
                    4,
                    4
                ],
                "max_atk": 3.0,
                "max_combo": 3,
                "min_atk": 3.0,
                "min_combo": 2,
                "name": "__어둠의 천사",
                "raw_description": "",
                "skill_id": 2342,
                "skill_type": 124
            }
        ],
        "name": "마소의 전령",
        "raw_description": "악마타입의 공격력과 회복력이 아주 조금 상승하고 어둠어둠 또는 어둠물 2콤보 이상일 때 공격력이 3배",
        "skill_id": 2472,
        "skill_type": 138
    },
    "na_skill": {
        "_atk": 1,
        "_hp": 1,
        "_rcv": 1,
        "_shield": 0,
        "child_ids": [
            2242,
            2342
        ],
        "child_skills": [
            {
                "_atk": 1.25,
                "_hp": 1.0,
                "_rcv": 1.25,
                "_shield": 0.0,
                "attributes": [],
                "name": "*****",
                "raw_description": "",
                "reduction_attributes": [],
                "skill_id": 2242,
                "skill_type": 129,
                "types": [
                    7
                ]
            },
            {
                "_atk": 3.0,
                "_hp": 1,
                "_rcv": 1,
                "_shield": 0,
                "atk_step": 0.0,
                "match_attributes": [
                    1,
                    4,
                    4
                ],
                "max_atk": 3.0,
                "max_combo": 3,
                "min_atk": 3.0,
                "min_combo": 2,
                "name": "*****",
                "raw_description": "",
                "skill_id": 2342,
                "skill_type": 124
            }
        ],
        "name": "Summoning Order",
        "raw_description": "Devil Type ATK & RCV increase slightly; 3x ATK with 2+ Dk+Dk or Dk+Wt combos",
        "skill_id": 2472,
        "skill_type": 138
    },
    "skill_id": 2472,
    "skill_type_tags": [
        "LsCondition.ENHANCED_ATK_RCV"
    ]
}